{
  "annotations": {
    "list": [
      {
        "builtIn": 1,
        "datasource": {
          "type": "grafana",
          "uid": "-- Grafana --"
        },
        "enable": true,
        "hide": true,
        "iconColor": "rgba(0, 211, 255, 1)",
        "name": "Annotations & Alerts",
        "type": "dashboard"
      }
    ]
  },
  "editable": true,
  "fiscalYearStartMonth": 0,
  "graphTooltip": 0,
  "id": null,
  "links": [],
  "liveNow": false,
  "panels": [
    {
      "collapsed": false,
      "gridPos": {
        "h": 1,
        "w": 24,
        "x": 0,
        "y": 0
      },
      "id": 15,
      "panels": [],
      "title": "Overview",
      "type": "row"
    },
    {
      "datasource": {
        "type": "prometheus",
        "uid": "Prometheus"
      },
      "fieldConfig": {
        "defaults": {
          "color": {
            "mode": "thresholds"
          },
          "mappings": [],
          "thresholds": {
            "mode": "absolute",
            "steps": [
              {
                "color": "green",
                "value": null
              },
              {
                "color": "yellow",
                "value": 50
              },
              {
                "color": "red",
                "value": 100
              }
            ]
          }
        },
        "overrides": []
      },
      "gridPos": {
        "h": 6,
        "w": 6,
        "x": 0,
        "y": 1
      },
      "id": 1,
      "options": {
        "orientation": "auto",
        "reduceOptions": {
          "calcs": [
            "lastNotNull"
          ],
          "fields": "",
          "values": false
        },
        "showThresholdLabels": false,
        "showThresholdMarkers": true,
        "text": {}
      },
      "pluginVersion": "9.5.3",
      "targets": [
        {
          "datasource": {
            "type": "prometheus",
            "uid": "Prometheus"
          },
          "editorMode": "builder",
          "expr": "sum(azure_servicebus_active_messages{environment=~\"$environment\", entity_type=~\"$entity_type\"})",
          "legendFormat": "__auto",
          "range": true,
          "refId": "A"
        }
      ],
      "title": "Total Active Messages",
      "type": "gauge"
    },
    {
      "datasource": {
        "type": "prometheus",
        "uid": "Prometheus"
      },
      "fieldConfig": {
        "defaults": {
          "color": {
            "mode": "thresholds"
          },
          "mappings": [],
          "thresholds": {
            "mode": "absolute",
            "steps": [
              {
                "color": "green",
                "value": null
              },
              {
                "color": "yellow",
                "value": 10
              },
              {
                "color": "red",
                "value": 50
              }
            ]
          }
        },
        "overrides": []
      },
      "gridPos": {
        "h": 6,
        "w": 6,
        "x": 6,
        "y": 1
      },
      "id": 2,
      "options": {
        "orientation": "auto",
        "reduceOptions": {
          "calcs": [
            "lastNotNull"
          ],
          "fields": "",
          "values": false
        },
        "showThresholdLabels": false,
        "showThresholdMarkers": true,
        "text": {}
      },
      "pluginVersion": "9.5.3",
      "targets": [
        {
          "datasource": {
            "type": "prometheus",
            "uid": "Prometheus"
          },
          "editorMode": "builder",
          "expr": "sum(azure_servicebus_dead_letter_messages{environment=~\"$environment\", entity_type=~\"$entity_type\"})",
          "legendFormat": "__auto",
          "range": true,
          "refId": "A"
        }
      ],
      "title": "Total Dead Letter Messages",
      "type": "gauge"
    },
    {
      "datasource": {
        "type": "prometheus",
        "uid": "Prometheus"
      },
      "fieldConfig": {
        "defaults": {
          "color": {
            "mode": "palette-classic"
          },
          "custom": {
            "hideFrom": {
              "legend": false,
              "tooltip": false,
              "viz": false
            }
          },
          "mappings": []
        },
        "overrides": []
      },
      "gridPos": {
        "h": 6,
        "w": 12,
        "x": 12,
        "y": 1
      },
      "id": 3,
      "options": {
        "displayLabels": ["name", "percent"],
        "legend": {
          "displayMode": "list",
          "placement": "right",
          "showLegend": true,
          "values": ["value"]
        },
        "pieType": "pie",
        "reduceOptions": {
          "calcs": [
            "lastNotNull"
          ],
          "fields": "",
          "values": false
        },
        "tooltip": {
          "mode": "single",
          "sort": "none"
        }
      },
      "pluginVersion": "9.5.3",
      "targets": [
        {
          "datasource": {
            "type": "prometheus",
            "uid": "Prometheus"
          },
          "editorMode": "builder",
          "expr": "sum by(environment) (azure_servicebus_active_messages{environment=~\"$environment\", entity_type=~\"$entity_type\"})",
          "legendFormat": "{{environment}}",
          "range": true,
          "refId": "A"
        }
      ],
      "title": "Messages by Environment",
      "type": "piechart"
    },
    {
      "datasource": {
        "type": "prometheus",
        "uid": "Prometheus"
      },
      "fieldConfig": {
        "defaults": {
          "color": {
            "mode": "palette-classic"
          },
          "custom": {
            "axisCenteredZero": false,
            "axisColorMode": "text",
            "axisLabel": "",
            "axisPlacement": "auto",
            "barAlignment": 0,
            "drawStyle": "line",
            "fillOpacity": 10,
            "gradientMode": "none",
            "hideFrom": {
              "legend": false,
              "tooltip": false,
              "viz": false
            },
            "lineInterpolation": "linear",
            "lineWidth": 1,
            "pointSize": 5,
            "scaleDistribution": {
              "type": "linear"
            },
            "showPoints": "never",
            "spanNulls": false,
            "stacking": {
              "group": "A",
              "mode": "none"
            },
            "thresholdsStyle": {
              "mode": "off"
            }
          },
          "mappings": [],
          "thresholds": {
            "mode": "absolute",
            "steps": [
              {
                "color": "green",
                "value": null
              },
              {
                "color": "red",
                "value": 80
              }
            ]
          },
          "unit": "short"
        },
        "overrides": []
      },
      "gridPos": {
        "h": 8,
        "w": 24,
        "x": 0,
        "y": 7
      },
      "id": 5,
      "options": {
        "legend": {
          "calcs": [
            "lastNotNull",
            "max",
            "mean"
          ],
          "displayMode": "table",
          "placement": "right",
          "showLegend": true
        },
        "tooltip": {
          "mode": "multi",
          "sort": "desc"
        }
      },
      "pluginVersion": "9.5.3",
      "targets": [
        {
          "datasource": {
            "type": "prometheus",
            "uid": "Prometheus"
          },
          "editorMode": "builder",
          "expr": "sum by(entity_name) (azure_servicebus_active_messages{environment=~\"$environment\", entity_type=\"queue\", entity_name=~\"$queue\"})",
          "legendFormat": "{{entity_name}}",
          "range": true,
          "refId": "A"
        }
      ],
      "title": "Active Messages by Queue",
      "type": "timeseries"
    },
    {
      "collapsed": false,
      "gridPos": {
        "h": 1,
        "w": 24,
        "x": 0,
        "y": 15
      },
      "id": 9,
      "panels": [],
      "title": "Queue Metrics",
      "type": "row"
    },
    {
      "datasource": {
        "type": "prometheus",
        "uid": "Prometheus"
      },
      "fieldConfig": {
        "defaults": {
          "color": {
            "mode": "palette-classic"
          },
          "custom": {
            "axisCenteredZero": false,
            "axisColorMode": "text",
            "axisLabel": "",
            "axisPlacement": "auto",
            "barAlignment": 0,
            "drawStyle": "line",
            "fillOpacity": 10,
            "gradientMode": "none",
            "hideFrom": {
              "legend": false,
              "tooltip": false,
              "viz": false
            },
            "lineInterpolation": "linear",
            "lineWidth": 1,
            "pointSize": 5,
            "scaleDistribution": {
              "type": "linear"
            },
            "showPoints": "never",
            "spanNulls": false,
            "stacking": {
              "group": "A",
              "mode": "none"
            },
            "thresholdsStyle": {
              "mode": "off"
            }
          },
          "mappings": [],
          "thresholds": {
            "mode": "absolute",
            "steps": [
              {
                "color": "green",
                "value": null
              }
            ]
          },
          "unit": "short"
        },
        "overrides": []
      },
      "gridPos": {
        "h": 8,
        "w": 12,
        "x": 0,
        "y": 16
      },
      "id": 4,
      "options": {
        "legend": {
          "calcs": [
            "lastNotNull",
            "max"
          ],
          "displayMode": "table",
          "placement": "bottom",
          "showLegend": true
        },
        "tooltip": {
          "mode": "multi",
          "sort": "desc"
        }
      },
      "pluginVersion": "9.5.3",
      "targets": [
        {
          "datasource": {
            "type": "prometheus",
            "uid": "Prometheus"
          },
          "editorMode": "builder",
          "expr": "azure_servicebus_dead_letter_messages{environment=~\"$environment\", entity_type=\"queue\", entity_name=~\"$queue\"}",
          "legendFormat": "{{entity_name}}",
          "range": true,
          "refId": "A"
        }
      ],
      "title": "Dead Letter Messages by Queue",
      "type": "timeseries"
    },
    {
      "datasource": {
        "type": "prometheus",
        "uid": "Prometheus"
      },
      "fieldConfig": {
        "defaults": {
          "color": {
            "mode": "palette-classic"
          },
          "custom": {
            "axisCenteredZero": false,
            "axisColorMode": "text",
            "axisLabel": "",
            "axisPlacement": "auto",
            "barAlignment": 0,
            "drawStyle": "line",
            "fillOpacity": 10,
            "gradientMode": "none",
            "hideFrom": {
              "legend": false,
              "tooltip": false,
              "viz": false
            },
            "lineInterpolation": "linear",
            "lineWidth": 1,
            "pointSize": 5,
            "scaleDistribution": {
              "type": "linear"
            },
            "showPoints": "never",
            "spanNulls": false,
            "stacking": {
              "group": "A",
              "mode": "none"
            },
            "thresholdsStyle": {
              "mode": "off"
            }
          },
          "mappings": [],
          "thresholds": {
            "mode": "absolute",
            "steps": [
              {
                "color": "green",
                "value": null
              }
            ]
          },
          "unit": "bytes"
        },
        "overrides": []
      },
      "gridPos": {
        "h": 8,
        "w": 12,
        "x": 12,
        "y": 16
      },
      "id": 8,
      "options": {
        "legend": {
          "calcs": [
            "lastNotNull",
            "max"
          ],
          "displayMode": "table",
          "placement": "bottom",
          "showLegend": true
        },
        "tooltip": {
          "mode": "multi",
          "sort": "desc"
        }
      },
      "pluginVersion": "9.5.3",
      "targets": [
        {
          "datasource": {
            "type": "prometheus",
            "uid": "Prometheus"
          },
          "editorMode": "builder",
          "expr": "azure_servicebus_size_bytes{environment=~\"$environment\", entity_type=\"queue\", entity_name=~\"$queue\"}",
          "legendFormat": "{{entity_name}}",
          "range": true,
          "refId": "A"
        }
      ],
      "title": "Queue Size (Bytes)",
      "type": "timeseries"
    },
    {
      "datasource": {
        "type": "prometheus",
        "uid": "Prometheus"
      },
      "fieldConfig": {
        "defaults": {
          "color": {
            "mode": "thresholds"
          },
          "custom": {
            "align": "auto",
            "cellOptions": {
              "type": "auto"
            },
            "inspect": false
          },
          "mappings": [],
          "thresholds": {
            "mode": "absolute",
            "steps": [
              {
                "color": "green",
                "value": null
              },
              {
                "color": "yellow",
                "value": 10
              },
              {
                "color": "red",
                "value": 100
              }
            ]
          }
        },
        "overrides": [
          {
            "matcher": {
              "id": "byName",
              "options": "entity_name"
            },
            "properties": [
              {
                "id": "displayName",
                "value": "Queue Name"
              }
            ]
          },
          {
            "matcher": {
              "id": "byName",
              "options": "environment"
            },
            "properties": [
              {
                "id": "displayName",
                "value": "Environment"
              }
            ]
          },
          {
            "matcher": {
              "id": "byName",
              "options": "Value"
            },
            "properties": [
              {
                "id": "displayName",
                "value": "Active Messages"
              },
              {
                "id": "custom.cellOptions",
                "value": {
                  "mode": "gradient",
                  "type": "color-background"
                }
              }
            ]
          }
        ]
      },
      "gridPos": {
        "h": 8,
        "w": 12,
        "x": 0,
        "y": 24
      },
      "id": 7,
      "options": {
        "cellHeight": "sm",
        "footer": {
          "countRows": false,
          "fields": "",
          "reducer": [
            "sum"
          ],
          "show": false
        },
        "showHeader": true,
        "sortBy": [
          {
            "desc": true,
            "displayName": "Active Messages"
          }
        ]
      },
      "pluginVersion": "9.5.3",
      "targets": [
        {
          "datasource": {
            "type": "prometheus",
            "uid": "Prometheus"
          },
          "editorMode": "builder",
          "exemplar": false,
          "expr": "azure_servicebus_active_messages{environment=~\"$environment\", entity_type=\"queue\", entity_name=~\"$queue\"}",
          "format": "table",
          "instant": true,
          "legendFormat": "__auto",
          "range": false,
          "refId": "A"
        }
      ],
      "title": "Current Queue Status",
      "transformations": [
        {
          "id": "organize",
          "options": {
            "excludeByName": {
              "__name__": true,
              "entity_type": true,
              "instance": true,
              "job": true,
              "namespace": true
            },
            "indexByName": {},
            "renameByName": {}
          }
        }
      ],
      "type": "table"
    },
    {
      "datasource": {
        "type": "prometheus",
        "uid": "Prometheus"
      },
      "fieldConfig": {
        "defaults": {
          "color": {
            "mode": "thresholds"
          },
          "custom": {
            "align": "auto",
            "cellOptions": {
              "type": "auto"
            },
            "inspect": false
          },
          "mappings": [],
          "thresholds": {
            "mode": "absolute",
            "steps": [
              {
                "color": "green",
                "value": null
              },
              {
                "color": "yellow",
                "value": 10
              },
              {
                "color": "red",
                "value": 50
              }
            ]
          }
        },
        "overrides": [
          {
            "matcher": {
              "id": "byName",
              "options": "entity_name"
            },
            "properties": [
              {
                "id": "displayName",
                "value": "Queue Name"
              }
            ]
          },
          {
            "matcher": {
              "id": "byName",
              "options": "environment"
            },
            "properties": [
              {
                "id": "displayName",
                "value": "Environment"
              }
            ]
          },
          {
            "matcher": {
              "id": "byName",
              "options": "Value"
            },
            "properties": [
              {
                "id": "displayName",
                "value": "Dead Letter Messages"
              },
              {
                "id": "custom.cellOptions",
                "value": {
                  "mode": "gradient",
                  "type": "color-background"
                }
              }
            ]
          }
        ]
      },
      "gridPos": {
        "h": 8,
        "w": 12,
        "x": 12,
        "y": 24
      },
      "id": 6,
      "options": {
        "cellHeight": "sm",
        "footer": {
          "countRows": false,
          "fields": "",
          "reducer": [
            "sum"
          ],
          "show": false
        },
        "showHeader": true,
        "sortBy": [
          {
            "desc": true,
            "displayName": "Dead Letter Messages"
          }
        ]
      },
      "pluginVersion": "9.5.3",
      "targets": [
        {
          "datasource": {
            "type": "prometheus",
            "uid": "Prometheus"
          },
          "editorMode": "builder",
          "exemplar": false,
          "expr": "azure_servicebus_dead_letter_messages{environment=~\"$environment\", entity_type=\"queue\", entity_name=~\"$queue\"}",
          "format": "table",
          "instant": true,
          "legendFormat": "__auto",
          "range": false,
          "refId": "A"
        }
      ],
      "title": "Dead Letter Status",
      "transformations": [
        {
          "id": "organize",
          "options": {
            "excludeByName": {
              "__name__": true,
              "entity_type": true,
              "instance": true,
              "job": true,
              "namespace": true
            },
            "indexByName": {},
            "renameByName": {}
          }
        }
      ],
      "type": "table"
    },
    {
      "collapsed": false,
      "gridPos": {
        "h": 1,
        "w": 24,
        "x": 0,
        "y": 32
      },
      "id": 100,
      "panels": [],
      "title": "Topics & Subscriptions",
      "type": "row"
    },
    {
      "datasource": {
        "type": "prometheus",
        "uid": "Prometheus"
      },
      "fieldConfig": {
        "defaults": {
          "color": {
            "mode": "palette-classic"
          },
          "custom": {
            "axisCenteredZero": false,
            "axisColorMode": "text",
            "axisLabel": "",
            "axisPlacement": "auto",
            "barAlignment": 0,
            "drawStyle": "line",
            "fillOpacity": 10,
            "gradientMode": "none",
            "hideFrom": {
              "legend": false,
              "tooltip": false,
              "viz": false
            },
            "lineInterpolation": "linear",
            "lineWidth": 1,
            "pointSize": 5,
            "scaleDistribution": {
              "type": "linear"
            },
            "showPoints": "never",
            "spanNulls": false,
            "stacking": {
              "group": "A",
              "mode": "none"
            },
            "thresholdsStyle": {
              "mode": "off"
            }
          },
          "mappings": [],
          "thresholds": {
            "mode": "absolute",
            "steps": [
              {
                "color": "green",
                "value": null
              }
            ]
          },
          "unit": "bytes"
        },
        "overrides": []
      },
      "gridPos": {
        "h": 8,
        "w": 12,
        "x": 0,
        "y": 33
      },
      "id": 101,
      "options": {
        "legend": {
          "calcs": [
            "lastNotNull",
            "max"
          ],
          "displayMode": "table",
          "placement": "bottom",
          "showLegend": true
        },
        "tooltip": {
          "mode": "multi",
          "sort": "desc"
        }
      },
      "pluginVersion": "9.5.3",
      "targets": [
        {
          "datasource": {
            "type": "prometheus",
            "uid": "Prometheus"
          },
          "editorMode": "builder",
          "expr": "azure_servicebus_size_bytes{environment=~\"$environment\", entity_type=\"topic\", entity_name=~\"$topic\"}",
          "legendFormat": "{{entity_name}}",
          "range": true,
          "refId": "A"
        }
      ],
      "title": "Topic Size (Bytes)",
      "type": "timeseries"
    },
    {
      "datasource": {
        "type": "prometheus",
        "uid": "Prometheus"
      },
      "fieldConfig": {
        "defaults": {
          "color": {
            "mode": "palette-classic"
          },
          "custom": {
            "axisCenteredZero": false,
            "axisColorMode": "text",
            "axisLabel": "",
            "axisPlacement": "auto",
            "barAlignment": 0,
            "drawStyle": "line",
            "fillOpacity": 10,
            "gradientMode": "none",
            "hideFrom": {
              "legend": false,
              "tooltip": false,
              "viz": false
            },
            "lineInterpolation": "linear",
            "lineWidth": 1,
            "pointSize": 5,
            "scaleDistribution": {
              "type": "linear"
            },
            "showPoints": "never",
            "spanNulls": false,
            "stacking": {
              "group": "A",
              "mode": "none"
            },
            "thresholdsStyle": {
              "mode": "off"
            }
          },
          "mappings": [],
          "thresholds": {
            "mode": "absolute",
            "steps": [
              {
                "color": "green",
                "value": null
              }
            ]
          },
          "unit": "short"
        },
        "overrides": []
      },
      "gridPos": {
        "h": 8,
        "w": 12,
        "x": 12,
        "y": 33
      },
      "id": 102,
      "options": {
        "legend": {
          "calcs": [
            "lastNotNull",
            "max"
          ],
          "displayMode": "table",
          "placement": "bottom",
          "showLegend": true
        },
        "tooltip": {
          "mode": "multi",
          "sort": "desc"
        }
      },
      "pluginVersion": "9.5.3",
      "targets": [
        {
          "datasource": {
            "type": "prometheus",
            "uid": "Prometheus"
          },
          "editorMode": "builder",
          "expr": "azure_servicebus_subscription_count{environment=~\"$environment\", entity_type=\"topic\", entity_name=~\"$topic\"}",
          "legendFormat": "{{entity_name}}",
          "range": true,
          "refId": "A"
        }
      ],
      "title": "Subscription Count by Topic",
      "type": "timeseries"
    },
    {
      "datasource": {
        "type": "prometheus",
        "uid": "Prometheus"
      },
      "fieldConfig": {
        "defaults": {
          "color": {
            "mode": "thresholds"
          },
          "custom": {
            "align": "auto",
            "cellOptions": {
              "type": "auto"
            },
            "inspect": false
          },
          "mappings": [],
          "thresholds": {
            "mode": "absolute",
            "steps": [
              {
                "color": "green",
                "value": null
              },
              {
                "color": "yellow",
                "value": 10
              },
              {
                "color": "red",
                "value": 100
              }
            ]
          }
        },
        "overrides": [
          {
            "matcher": {
              "id": "byName",
              "options": "entity_name"
            },
            "properties": [
              {
                "id": "displayName",
                "value": "Topic Name"
              }
            ]
          },
          {
            "matcher": {
              "id": "byName",
              "options": "environment"
            },
            "properties": [
              {
                "id": "displayName",
                "value": "Environment"
              }
            ]
          },
          {
            "matcher": {
              "id": "byName",
              "options": "Value"
            },
            "properties": [
              {
                "id": "displayName",
                "value": "Size (Bytes)"
              },
              {
                "id": "custom.cellOptions",
                "value": {
                  "mode": "gradient",
                  "type": "color-background"
                }
              }
            ]
          }
        ]
      },
      "gridPos": {
        "h": 8,
        "w": 24,
        "x": 0,
        "y": 41
      },
      "id": 103,
      "options": {
        "cellHeight": "sm",
        "footer": {
          "countRows": false,
          "fields": "",
          "reducer": [
            "sum"
          ],
          "show": false
        },
        "showHeader": true,
        "sortBy": [
          {
            "desc": true,
            "displayName": "Size (Bytes)"
          }
        ]
      },
      "pluginVersion": "9.5.3",
      "targets": [
        {
          "datasource": {
            "type": "prometheus",
            "uid": "Prometheus"
          },
          "editorMode": "builder",
          "exemplar": false,
          "expr": "azure_servicebus_size_bytes{environment=~\"$environment\", entity_type=\"topic\", entity_name=~\"$topic\"}",
          "format": "table",
          "instant": true,
          "legendFormat": "__auto",
          "range": false,
          "refId": "A"
        }
      ],
      "title": "Current Topic Status",
      "transformations": [
        {
          "id": "organize",
          "options": {
            "excludeByName": {
              "__name__": true,
              "entity_type": true,
              "instance": true,
              "job": true,
              "namespace": true
            },
            "indexByName": {},
            "renameByName": {}
          }
        }
      ],
      "type": "table"
    },
    {
      "datasource": {
        "type": "prometheus",
        "uid": "Prometheus"
      },
      "fieldConfig": {
        "defaults": {
          "color": {
            "mode": "palette-classic"
          },
          "custom": {
            "axisCenteredZero": false,
            "axisColorMode": "text",
            "axisLabel": "",
            "axisPlacement": "auto",
            "barAlignment": 0,
            "drawStyle": "line",
            "fillOpacity": 10,
            "gradientMode": "none",
            "hideFrom": {
              "legend": false,
              "tooltip": false,
              "viz": false
            },
            "lineInterpolation": "linear",
            "lineWidth": 1,
            "pointSize": 5,
            "scaleDistribution": {
              "type": "linear"
            },
            "showPoints": "never",
            "spanNulls": false,
            "stacking": {
              "group": "A",
              "mode": "none"
            },
            "thresholdsStyle": {
              "mode": "off"
            }
          },
          "mappings": [],
          "thresholds": {
            "mode": "absolute",
            "steps": [
              {
                "color": "green",
                "value": null
              },
              {
                "color": "red",
                "value": 80
              }
            ]
          },
          "unit": "short"
        },
        "overrides": []
      },
      "gridPos": {
        "h": 8,
        "w": 12,
        "x": 0,
        "y": 49
      },
      "id": 104,
      "options": {
        "legend": {
          "calcs": [
            "lastNotNull",
            "max",
            "mean"
          ],
          "displayMode": "table",
          "placement": "right",
          "showLegend": true
        },
        "tooltip": {
          "mode": "multi",
          "sort": "desc"
        }
      },
      "pluginVersion": "9.5.3",
      "targets": [
        {
          "datasource": {
            "type": "prometheus",
            "uid": "Prometheus"
          },
          "editorMode": "builder",
          "expr": "azure_servicebus_active_messages{environment=~\"$environment\", entity_type=\"subscription\", topic_name=~\"$topic\", subscription_name=~\"$subscription\"}",
          "legendFormat": "{{topic_name}}/{{subscription_name}}",
          "range": true,
          "refId": "A"
        }
      ],
      "title": "Active Messages by Subscription",
      "type": "timeseries"
    },
    {
      "datasource": {
        "type": "prometheus",
        "uid": "Prometheus"
      },
      "fieldConfig": {
        "defaults": {
          "color": {
            "mode": "palette-classic"
          },
          "custom": {
            "axisCenteredZero": false,
            "axisColorMode": "text",
            "axisLabel": "",
            "axisPlacement": "auto",
            "barAlignment": 0,
            "drawStyle": "line",
            "fillOpacity": 10,
            "gradientMode": "none",
            "hideFrom": {
              "legend": false,
              "tooltip": false,
              "viz": false
            },
            "lineInterpolation": "linear",
            "lineWidth": 1,
            "pointSize": 5,
            "scaleDistribution": {
              "type": "linear"
            },
            "showPoints": "never",
            "spanNulls": false,
            "stacking": {
              "group": "A",
              "mode": "none"
            },
            "thresholdsStyle": {
              "mode": "off"
            }
          },
          "mappings": [],
          "thresholds": {
            "mode": "absolute",
            "steps": [
              {
                "color": "green",
                "value": null
              },
              {
                "color": "red",
                "value": 80
              }
            ]
          },
          "unit": "short"
        },
        "overrides": []
      },
      "gridPos": {
        "h": 8,
        "w": 12,
        "x": 12,
        "y": 49
      },
      "id": 105,
      "options": {
        "legend": {
          "calcs": [
            "lastNotNull",
            "max",
            "mean"
          ],
          "displayMode": "table",
          "placement": "right",
          "showLegend": true
        },
        "tooltip": {
          "mode": "multi",
          "sort": "desc"
        }
      },
      "pluginVersion": "9.5.3",
      "targets": [
        {
          "datasource": {
            "type": "prometheus",
            "uid": "Prometheus"
          },
          "editorMode": "builder",
          "expr": "azure_servicebus_dead_letter_messages{environment=~\"$environment\", entity_type=\"subscription\", topic_name=~\"$topic\", subscription_name=~\"$subscription\"}",
          "legendFormat": "{{topic_name}}/{{subscription_name}}",
          "range": true,
          "refId": "A"
        }
      ],
      "title": "Dead Letter Messages by Subscription",
      "type": "timeseries"
    },
    {
      "datasource": {
        "type": "prometheus",
        "uid": "Prometheus"
      },
      "fieldConfig": {
        "defaults": {
          "color": {
            "mode": "thresholds"
          },
          "custom": {
            "align": "auto",
            "cellOptions": {
              "type": "auto"
            },
            "inspect": false
          },
          "mappings": [],
          "thresholds": {
            "mode": "absolute",
            "steps": [
              {
                "color": "green",
                "value": null
              },
              {
                "color": "yellow",
                "value": 10
              },
              {
                "color": "red",
                "value": 100
              }
            ]
          }
        },
        "overrides": [
          {
            "matcher": {
              "id": "byName",
              "options": "topic_name"
            },
            "properties": [
              {
                "id": "displayName",
                "value": "Topic"
              }
            ]
          },
          {
            "matcher": {
              "id": "byName",
              "options": "subscription_name"
            },
            "properties": [
              {
                "id": "displayName",
                "value": "Subscription"
              }
            ]
          },
          {
            "matcher": {
              "id": "byName",
              "options": "environment"
            },
            "properties": [
              {
                "id": "displayName",
                "value": "Environment"
              }
            ]
          },
          {
            "matcher": {
              "id": "byName",
              "options": "Value"
            },
            "properties": [
              {
                "id": "displayName",
                "value": "Active Messages"
              },
              {
                "id": "custom.cellOptions",
                "value": {
                  "mode": "gradient",
                  "type": "color-background"
                }
              }
            ]
          }
        ]
      },
      "gridPos": {
        "h": 8,
        "w": 24,
        "x": 0,
        "y": 57
      },
      "id": 106,
      "options": {
        "cellHeight": "sm",
        "footer": {
          "countRows": false,
          "fields": "",
          "reducer": [
            "sum"
          ],
          "show": false
        },
        "showHeader": true,
        "sortBy": [
          {
            "desc": true,
            "displayName": "Active Messages"
          }
        ]
      },
      "pluginVersion": "9.5.3",
      "targets": [
        {
          "datasource": {
            "type": "prometheus",
            "uid": "Prometheus"
          },
          "editorMode": "builder",
          "exemplar": false,
          "expr": "azure_servicebus_active_messages{environment=~\"$environment\", entity_type=\"subscription\", topic_name=~\"$topic\", subscription_name=~\"$subscription\"}",
          "format": "table",
          "instant": true,
          "legendFormat": "__auto",
          "range": false,
          "refId": "A"
        }
      ],
      "title": "Current Subscription Status",
      "transformations": [
        {
          "id": "organize",
          "options": {
            "excludeByName": {
              "__name__": true,
              "entity_name": true,
              "entity_type": true,
              "instance": true,
              "job": true,
              "namespace": true
            },
            "indexByName": {},
            "renameByName": {}
          }
        }
      ],
      "type": "table"
    }
  ],
  "refresh": "10s",
  "schemaVersion": 38,
  "style": "dark",
  "tags": [
    "azure",
    "servicebus",
    "metrics"
  ],
  "templating": {
    "list": [
      {
        "current": {
          "selected": false,
          "text": "All",
          "value": "$__all"
        },
        "datasource": {
          "type": "prometheus",
          "uid": "Prometheus"
        },
        "definition": "label_values(azure_servicebus_active_messages, environment)",
        "hide": 0,
        "includeAll": true,
        "label": "Environment",
        "multi": false,
        "name": "environment",
        "options": [],
        "query": {
          "query": "label_values(azure_servicebus_active_messages, environment)",
          "refId": "StandardVariableQuery"
        },
        "refresh": 1,
        "regex": "",
        "skipUrlSync": false,
        "sort": 1,
        "type": "query"
      },
      {
        "current": {
          "selected": false,
          "text": "All",
          "value": "$__all"
        },
        "datasource": {
          "type": "prometheus",
          "uid": "Prometheus"
        },
        "definition": "label_values(azure_servicebus_active_messages{environment=~\"$environment\"}, entity_name)",
        "hide": 0,
        "includeAll": true,
        "label": "Queue",
        "multi": false,
        "name": "queue",
        "options": [],
        "query": {
          "query": "label_values(azure_servicebus_active_messages{environment=~\"$environment\"}, entity_name)",
          "refId": "StandardVariableQuery"
        },
        "refresh": 1,
        "regex": "",
        "skipUrlSync": false,
        "sort": 1,
        "type": "query"
      },
      {
        "current": {
          "selected": false,
          "text": "All",
          "value": "$__all"
        },
        "datasource": {
          "type": "prometheus",
          "uid": "Prometheus"
        },
        "definition": "label_values(azure_servicebus_size_bytes{entity_type=\"topic\", environment=~\"$environment\"}, entity_name)",
        "hide": 0,
        "includeAll": true,
        "label": "Topic",
        "multi": false,
        "name": "topic",
        "options": [],
        "query": {
          "query": "label_values(azure_servicebus_size_bytes{entity_type=\"topic\", environment=~\"$environment\"}, entity_name)",
          "refId": "StandardVariableQuery"
        },
        "refresh": 1,
        "regex": "",
        "skipUrlSync": false,
        "sort": 1,
        "type": "query"
      },
      {
        "current": {
          "selected": false,
          "text": "All",
          "value": "$__all"
        },
        "datasource": {
          "type": "prometheus",
          "uid": "Prometheus"
        },
        "definition": "label_values(azure_servicebus_active_messages{entity_type=\"subscription\", environment=~\"$environment\"}, subscription_name)",
        "hide": 0,
        "includeAll": true,
        "label": "Subscription",
        "multi": false,
        "name": "subscription",
        "options": [],
        "query": {
          "query": "label_values(azure_servicebus_active_messages{entity_type=\"subscription\", environment=~\"$environment\"}, subscription_name)",
          "refId": "StandardVariableQuery"
        },
        "refresh": 1,
        "regex": "",
        "skipUrlSync": false,
        "sort": 1,
        "type": "query"
      },
      {
        "current": {
          "selected": false,
          "text": "All",
          "value": "$__all"
        },
        "datasource": {
          "type": "prometheus",
          "uid": "Prometheus"
        },
        "definition": "label_values(azure_servicebus_active_messages, entity_type)",
        "hide": 0,
        "includeAll": true,
        "label": "Entity Type",
        "multi": false,
        "name": "entity_type",
        "options": [],
        "query": {
          "query": "label_values(azure_servicebus_active_messages, entity_type)",
          "refId": "StandardVariableQuery"
        },
        "refresh": 1,
        "regex": "",
        "skipUrlSync": false,
        "sort": 1,
        "type": "query"
      }
    ]
  },
  "time": {
    "from": "now-1h",
    "to": "now"
  },
  "timepicker": {
    "refresh_intervals": [
      "5s",
      "10s",
      "30s",
      "1m",
      "5m",
      "15m",
      "30m",
      "1h",
      "2h",
      "1d"
    ]
  },
  "timezone": "",
  "title": "Azure Service Bus Metrics Dashboard",
  "uid": "azure-servicebus-metrics",
  "version": 1,
  "weekStart": ""
}
